certainly_not_python_client-10.0.4.dist-info/licenses/LICENSE
notifications_python_client/__init__.py
notifications_python_client/authentication.py
notifications_python_client/base.py
notifications_python_client/errors.py
notifications_python_client/notifications.py
notifications_python_client/py.typed
certainly_not_python_client-10.0.4.dist-info/METADATA
certainly_not_python_client-10.0.4.dist-info/WHEEL
certainly_not_python_client-10.0.4.dist-info/top_level.txt
certainly_not_python_client-10.0.4.dist-info/RECORD
