Metadata-Version: 2.4
Name: certainly-not-python-client
Version: 10.0.4
Summary: Python API client for La Plateforme gouvernementale de notification.
Home-page: https://github.com/jpbelang/certainly-not-python-client
Author: Ministère de la Cybersécurité et du numérique (MCN)
License: LiLiQ-Rplus-1.1
Keywords: pgn gouvqc notification
Classifier: Intended Audience :: Developers
Classifier: Development Status :: 4 - Beta
Classifier: Programming Language :: Python :: 3 :: Only
Classifier: Programming Language :: Python :: 3.8
Classifier: Programming Language :: Python :: 3.9
Classifier: Programming Language :: Python :: 3.10
Classifier: Programming Language :: Python :: 3.11
Classifier: Programming Language :: Python :: 3.12
Requires-Python: >=3.8
License-File: LICENSE
Requires-Dist: requests>=2.0.0
Requires-Dist: PyJWT>=1.5.1
Requires-Dist: docopt>=0.3.0
Dynamic: author
Dynamic: classifier
Dynamic: description
Dynamic: home-page
Dynamic: keywords
Dynamic: license
Dynamic: license-file
Dynamic: requires-dist
Dynamic: requires-python
Dynamic: summary
